[
  {
    "id": 5706,
    "title": "Mark of Calth",
    "year": 2013,
    "type": "novel",
    "imageName": "lg_markofca.jpg",
    "nominations": 0,
    "wins": -1
  },
  {
    "id": 13095,
    "title": "Legacies of Betrayal:  Let the galaxy burn",
    "year": 2015,
    "type": "novel",
    "imageName": "uc_legacies.jpg",
    "nominations": 0,
    "wins": -1
  },
  {
    "id": 17815,
    "title": "Eye of Terra",
    "year": 2016,
    "type": "novel",
    "imageName": "hh_eyeofter.jpg",
    "nominations": 0,
    "wins": -1
  },
  {
    "id": 26162,
    "title": "The Silent War",
    "year": 2016,
    "type": "novel",
    "imageName": "lg_thesilen.jpg",
    "nominations": 0,
    "wins": -1
  },
  {
    "id": 26168,
    "title": "Shattered Legions",
    "year": 2017,
    "type": "novel",
    "imageName": "lg_shattere.jpg",
    "nominations": 0,
    "wins": -1
  },
  {
    "id": 26943,
    "title": "The Burden of Loyalty",
    "year": 2018,
    "type": "novel",
    "imageName": "lg_theburde.jpg",
    "nominations": 0,
    "wins": -1
  },
  {
    "id": 31645,
    "title": "Heralds of the Siege",
    "year": 2019,
    "type": "novel",
    "imageName": "nklg_heraldso.jpg",
    "nominations": 0,
    "wins": -1
  },
  {
    "id": 15471,
    "title": "Lost Tales",
    "year": 2013,
    "type": "novel",
    "imageName": "lg_losttale.jpg",
    "nominations": 0,
    "wins": -1
  }
]