[
  {
    "id": 21503,
    "title": "The Duplicators / No Truce with Terra",
    "year": 1964,
    "type": "novel",
    "imageName": "ad_thedupli_notrucew.gif",
    "nominations": 0,
    "wins": -1
  },
  {
    "id": 21509,
    "title": "Reality Forbidden / Contraband From Otherspace",
    "year": 1967,
    "type": "novel",
    "imageName": "ad_realityf_contraba.gif",
    "nominations": 0,
    "wins": -1
  },
  {
    "id": 21511,
    "title": "These Savage Futurians / The Double Invaders",
    "year": 1967,
    "type": "novel",
    "imageName": "ad_thesesav_thedoubl.gif",
    "nominations": 0,
    "wins": -1
  },
  {
    "id": 21644,
    "title": "Anthropol / The Time Mercenaries",
    "year": 1968,
    "type": "novel",
    "imageName": "ad_anthropo_thetimem.gif",
    "nominations": 0,
    "wins": -1
  },
  {
    "id": 21555,
    "title": "Invader on My Back / Destination: Saturn",
    "year": 1968,
    "type": "novel",
    "imageName": "ad_invadero_destinat.gif",
    "nominations": 0,
    "wins": -1
  },
  {
    "id": 21505,
    "title": "Space Captain / The Mad Metropolis",
    "year": 1966,
    "type": "novel",
    "imageName": "ad_spacecap_themadme.gif",
    "nominations": 0,
    "wins": -1
  }
]