[
  {
    "id": 22183,
    "title": "At the Edge of Waking",
    "year": 2012,
    "type": "novel",
    "imageName": "HP_edgewake.jpg",
    "nominations": 0,
    "wins": -1
  },
  {
    "id": 28872,
    "title": "The Long, Cold Goodbye",
    "year": 2009,
    "type": "novelette",
    "nominations": 0,
    "wins": -1
  },
  {
    "id": 22181,
    "title": "The Engine's Child",
    "year": 2008,
    "type": "novel",
    "imageName": "HP_enginesc.jpg",
    "nominations": 0,
    "wins": -1
  },
  {
    "id": 26433,
    "title": "The Small Door",
    "year": 2008,
    "type": "short-story",
    "nominations": 0,
    "wins": -1
  },
  {
    "id": 30288,
    "title": "Brother of the Moon",
    "year": 2007,
    "type": "short-story",
    "nominations": 0,
    "wins": -1
  },
  {
    "id": 25146,
    "title": "The Oracle Spoke",
    "year": 2007,
    "type": "short-story",
    "nominations": 0,
    "wins": -1
  },
  {
    "id": 22618,
    "title": "Three Days of Rain",
    "year": 2007,
    "type": "short-story",
    "nominations": 0,
    "wins": -1
  },
  {
    "id": 22180,
    "title": "The Burning Girl",
    "year": 2006,
    "type": "novel",
    "imageName": "HP_burning.jpg",
    "nominations": 0,
    "wins": -1
  },
  {
    "id": 31778,
    "title": "By the Light of Tomorrow's Sun",
    "year": 2005,
    "type": "short-story",
    "nominations": 0,
    "wins": -1
  },
  {
    "id": 22182,
    "title": "In the Palace of Repose",
    "year": 2005,
    "type": "novel",
    "imageName": "HP_palaceof.jpg",
    "nominations": 0,
    "wins": -1
  },
  {
    "id": 24135,
    "title": "The Other Grace",
    "year": 2005,
    "type": "novelette",
    "nominations": 0,
    "wins": -1
  }
]